msoffice2pdf/__init__.py
msoffice2pdf-0.0.8.dist-info/LICENSE
msoffice2pdf-0.0.8.dist-info/METADATA
msoffice2pdf-0.0.8.dist-info/WHEEL
msoffice2pdf-0.0.8.dist-info/top_level.txt
msoffice2pdf-0.0.8.dist-info/RECORD
