Metadata-Version: 2.1
Name: msoffice2pdf
Version: 0.0.8
Summary: This package aims to convert Office file types to PDF using Microsoft Office or LibreOffice.
Home-page: https://github.com/robsonlimadeveloper/msoffice2pdf
Author: Robson Soares de Lima
Author-email: robsonlimadeveloper@gmail.com
License: UNKNOWN
Project-URL: Bug Tracker, https://github.com/robsonlimadeveloper/msoffice2pdf/issues
Platform: UNKNOWN
Classifier: Programming Language :: Python :: 3
Classifier: License :: OSI Approved :: MIT License
Classifier: Environment :: Win32 (MS Windows)
Classifier: Operating System :: Microsoft :: Windows
Classifier: Operating System :: Unix
Classifier: Topic :: Software Development
Classifier: Topic :: Office/Business :: Office Suites
Classifier: Topic :: Software Development :: Libraries
Classifier: Topic :: Software Development :: Libraries :: Python Modules
Classifier: Topic :: System :: Filesystems
Classifier: Topic :: Utilities
Classifier: Topic :: Text Processing :: General
Requires-Python: >=3.6
License-File: LICENSE
